sx126x/__init__.py
sx126x/sx126x.py
sx126x/util.py
sx126x/enums/__init__.py
sx126x/enums/air_speed.py
sx126x/enums/ambient_noise.py
sx126x/enums/baud_rate.py
sx126x/enums/command.py
sx126x/enums/lbt.py
sx126x/enums/mode.py
sx126x/enums/packet_size.py
sx126x/enums/parity.py
sx126x/enums/register.py
sx126x/enums/relay.py
sx126x/enums/rssi.py
sx126x/enums/transfer_method.py
sx126x/enums/transmit_power.py
sx126x/enums/wor_control.py
sx126x/enums/wor_period.py
sx126x/models/__init__.py
sx126x/models/address.py
sx126x/models/crypt_key.py
sx126x-2.2.4.dist-info/METADATA
sx126x-2.2.4.dist-info/WHEEL
sx126x-2.2.4.dist-info/licenses/LICENSE
sx126x-2.2.4.dist-info/RECORD
