Metadata-Version: 2.4
Name: sx126x
Version: 2.2.4
Project-URL: Homepage, https://github.com/nbdy/pysx126x
Project-URL: Documentation, https://github.com/nbdy/pysx126x/wiki
Project-URL: Repository, https://github.com/nbdy/pysx126x.git
Project-URL: Issues, https://github.com/nbdy/pysx126x/issues
Author: nbdy
Maintainer: nbdy
License: MIT License
License-File: LICENSE
Keywords: lora,sx126x
Classifier: Development Status :: 4 - Beta
Classifier: License :: OSI Approved :: MIT License
Classifier: Programming Language :: Python :: 3.11
Classifier: Programming Language :: Python :: 3.12
Requires-Python: >=3.9
Requires-Dist: loguru==0.7.3
Requires-Dist: pyserial==3.5
Requires-Dist: rpi-gpio==0.7.1
Provides-Extra: dev
Requires-Dist: pytest>=8.4.2; extra == 'dev'
